pyqttango/__init__.py
pyqttango/_version.py
pyqttango/tango.rcc
pyqttango/test.py
pyqttango-0.2.0.dist-info/LICENSE
pyqttango-0.2.0.dist-info/METADATA
pyqttango-0.2.0.dist-info/WHEEL
pyqttango-0.2.0.dist-info/top_level.txt
pyqttango-0.2.0.dist-info/RECORD
