Metadata-Version: 2.1
Name: pyqttango
Version: 0.2.0
Summary: Qt resource file containing Tango freedesktop.org icons
Home-page: https://github.com/ppinard/pyqttango
Author: Philippe T. Pinard
Author-email: philippe.pinard@gmail.com
License: Apache Software License 2.0
Platform: UNKNOWN
Classifier: Development Status :: 4 - Beta
Classifier: Intended Audience :: End Users/Desktop
Classifier: License :: OSI Approved :: GNU General Public License (GPL)
Classifier: Natural Language :: English
Classifier: Programming Language :: Python
Classifier: Operating System :: OS Independent
Requires-Dist: qtpy
Provides-Extra: develop
Requires-Dist: nose ; extra == 'develop'
Requires-Dist: coverage ; extra == 'develop'
Requires-Dist: requests ; extra == 'develop'
Requires-Dist: requests-download ; extra == 'develop'
Requires-Dist: tqdm ; extra == 'develop'
